bytedloadbalance/__init__.py
bytedloadbalance-0.0.1.dist-info/METADATA
bytedloadbalance-0.0.1.dist-info/WHEEL
bytedloadbalance-0.0.1.dist-info/top_level.txt
bytedloadbalance-0.0.1.dist-info/RECORD
